[
  {"q": "বাক্যস্থিত ক্রিয়া পদের সাথে নাম পদের সম্পর্ককে কী বলে?", "o": ["কারক", "সমাস", "সন্ধি", "বিভক্তি"], "a": 0, "e": "ক্রিয়া পদের সাথে নাম পদের সরাসরি সম্পর্কই হলো কারক।"},
  {"q": "কারক কয় প্রকার?", "o": ["৪ প্রকার", "৫ প্রকার", "৬ প্রকার", "৭ প্রকার"], "a": 2, "e": "কারক মোট ৬ প্রকার: কর্তৃ, কর্ম, করণ, সম্প্রদান, অপাদান ও অধিকরণ।"},
  {"q": "‘বুলবুলিতে ধান খেয়েছে’ - এখানে ‘বুলবুলিতে’ কোন কারক?", "o": ["কর্তৃকারক", "কর্মকারক", "করণকারক", "অপাদান"], "a": 0, "e": "ক্রিয়া যে সম্পন্ন করে সে কর্তৃকারক।"},
  {"q": "‘পাগলে কি না বলে’ - ‘পাগলে’ কোন কারকে কোন বিভক্তি?", "o": ["কর্তায় ৭মী", "কর্মে ৭মী", "করণে ৭মী", "অপাদানে ৭মী"], "a": 0, "e": "পাগল এখানে কর্তা, আর 'এ' বিভক্তি হলো ৭মী।"},
  {"q": "‘টাকায় টাকা হয়’ - ‘টাকায়’ কোন কারক?", "o": ["কর্তা", "করণ", "অপাদান", "অধিকরণ"], "a": 2, "e": "যা থেকে কিছু উৎপন্ন বা বিচ্যুত হয় তা অপাদান।"},
  {"q": "‘অস্ত্রের মুখে শত্রু নত হলো’ - ‘অস্ত্রের’ কোন কারক?", "o": ["কর্তা", "কর্ম", "করণ", "অধিকরণ"], "a": 2, "e": "অস্ত্র এখানে ক্রিয়া সম্পাদনের যন্ত্র বা উপায়।"},
  {"q": "‘ভিক্ষুককে ভিক্ষা দাও’ - ‘ভিক্ষুককে’ কোন কারক?", "o": ["কর্ম", "করণ", "সম্প্রদান", "অপাদান"], "a": 2, "e": "স্বত্ব ত্যাগ করে দান করা বোঝালে সম্প্রদান কারক হয়।"},
  {"q": "‘তিলে তৈল আছে’ - ‘তিলে’ কোন কারক?", "o": ["অপাদান", "অধিকরণ", "কর্ম", "করণ"], "a": 1, "e": "কোনো স্থানে কিছু বিদ্যমান থাকলে তা অধিকরণ।"},
  {"q": "‘তিলে তৈল হয়’ - ‘তিলে’ কোন কারক?", "o": ["অপাদান", "অধিকরণ", "কর্ম", "করণ"], "a": 0, "e": "তিল থেকে তৈল বের করা হয় বলে এটি অপাদান।"},
  {"q": "‘বাড়ি থেকে নদী দেখা যায়’ - ‘বাড়ি থেকে’ কোন কারক?", "o": ["অপাদান", "অধিকরণ", "করণ", "কর্ম"], "a": 1, "e": "নির্দিষ্ট স্থান থেকে দেখা যাচ্ছে, তাই এটি অধিকরণ।"},
  {"q": "‘ছেলেরা ফুটবল খেলছে’ - ‘ফুটবল’ কোন কারক?", "o": ["কর্তা", "কর্ম", "করণ", "অপাদান"], "a": 1, "e": "যাকে আশ্রয় করে ক্রিয়া সম্পাদিত হয় তা কর্মকারক।"},
  {"q": "‘নৌকা ঘাটে বাঁধা’ - ‘ঘাটে’ কোন কারক?", "o": ["অপাদান", "অধিকরণ", "করণ", "কর্ম"], "a": 1, "e": "স্থান বোঝালে অধিকরণ কারক হয়।"},
  {"q": "‘ট্রেন স্টেশন ছেড়েছে’ - ‘স্টেশন’ কোন কারক?", "o": ["অপাদান", "অধিকরণ", "করণ", "কর্ম"], "a": 0, "e": "বিচ্যুত হওয়া বোঝালে অপাদান কারক হয়।"},
  {"q": "‘টাকায় সব হয়’ - ‘টাকায়’ কোন কারক?", "o": ["কর্তা", "কর্ম", "করণ", "অপাদান"], "a": 2, "e": "টাকার দ্বারা কাজ সম্পন্ন হচ্ছে, তাই করণ।"},
  {"q": "‘সর্বাঙ্গে ব্যথা ওষুধ দিব কোথা’ - ‘সর্বাঙ্গে’ কোন কারক?", "o": ["অধিকরণ", "অপাদান", "করণ", "কর্ম"], "a": 0, "e": "শরীরের সব স্থান বোঝাচ্ছে বিধায় অধিকরণ।"},
  {"q": "‘জলে কুমির ডাঙায় বাঘ’ - ‘জলে’ কোন কারক?", "o": ["অধিকরণ", "অপাদান", "করণ", "কর্ম"], "a": 0, "e": "স্থানবাচক অধিকরণ কারক।"},
  {"q": "‘কালনেমি মামার লঙ্কাপূরী’ - ‘কালনেমি’ কোন পদ?", "o": ["কর্তা", "কর্ম", "সম্বন্ধ পদ", "অধিকরণ"], "a": 2, "e": "কারকের সাথে সম্পর্কহীন পদ সম্বন্ধ পদ।"},
  {"q": "‘বিপদে মোরে রক্ষা করো’ - ‘বিপদে’ কোন কারক?", "o": ["কর্তা", "অপাদান", "অধিকরণ", "করণ"], "a": 1, "e": "বিপদ থেকে ভীতি বা রক্ষা পাওয়া অপাদান।"},
  {"q": "‘গগনে গরজে মেঘ’ - ‘গগনে’ কোন কারক?", "o": ["অধিকরণ", "অপাদান", "করণ", "কর্ম"], "a": 0, "e": "গগন বা আকাশ এখানে স্থান।"},
  {"q": "‘কাননে কুসুম কলি সকলি ফুটিল’ - ‘কাননে’ কোন কারক?", "o": ["অধিকরণ", "অপাদান", "করণ", "কর্ম"], "a": 0, "e": "কানন বা বাগান স্থান বোঝাচ্ছে।"},
  {"q": "‘হীরামনকে খাঁচায় ভরো’ - ‘খাঁচায়’ কোন কারক?", "o": ["অধিকরণ", "অপাদান", "করণ", "কর্ম"], "a": 0, "e": "খাঁচা একটি আধার বা স্থান।"},
  {"q": "‘একুশে ফেব্রুয়ারি আমাদের গর্ব’ - ‘একুশে’ কোন কারক?", "o": ["কালাধিকরণ", "আধারাধিকরণ", "ভাবাধিকরণ", "অপাদান"], "a": 0, "e": "সময় বোঝালে কালাধিকরণ হয়।"},
  {"q": "‘প্রভাতে সূর্য ওঠে’ - ‘প্রভাতে’ কোন কারক?", "o": ["অধিকরণ", "অপাদান", "করণ", "কর্ম"], "a": 0, "e": "সময়বাচক অধিকরণ।"},
  {"q": "‘বড়ো যদি হতে চাও ছোট হও তবে’ - ‘ছোট’ কোন কারক?", "o": ["কর্ম", "কর্তা", "করণ", "অধিকরণ"], "a": 0, "e": "ক্রিয়ার কর্ম হিসেবে ব্যবহৃত।"},
  {"q": "‘আমি বই পড়ি’ - ‘বই’ কোন কারক?", "o": ["কর্তা", "কর্ম", "করণ", "অপাদান"], "a": 1, "e": "কী পড়ি? উত্তর বই, তাই এটি কর্ম।"},
  {"q": "‘সাপুড়ে সাপ খেলায়’ - ‘সাপ’ কোন কারক?", "o": ["কর্তা", "কর্ম", "করণ", "অপাদান"], "a": 1, "e": "কর্তা যাকে দিয়ে কাজ করায় তা প্রযোজ্য কর্ম।"},
  {"q": "‘বেলা যে পড়ে এল জলকে চল’ - ‘জলকে’ কোন কারক?", "o": ["কর্ম", "করণ", "সম্প্রদান", "নিমিত্তার্থ"], "a": 3, "e": "জলের নিমিত্ত বা উদ্দেশ্যে যাওয়া।"},
  {"q": "‘দরিদ্রকে সাহায্য করো’ - ‘দরিদ্রকে’ কোন কারক?", "o": ["কর্ম", "করণ", "সম্প্রদান", "অপাদান"], "a": 2, "e": "নিঃস্বার্থ দান বোঝালে সম্প্রদান।"},
  {"q": "‘পাছে লোকে কিছু বলে’ - ‘লোকে’ কোন কারক?", "o": ["কর্তা", "কর্ম", "করণ", "অধিকরণ"], "a": 0, "e": "কথা বলার কাজটি লোকে করে।"},
  {"q": "‘চোখ দিয়ে জল পড়ে’ - ‘চোখ দিয়ে’ কোন কারক?", "o": ["করণ", "অপাদান", "অধিকরণ", "কর্ম"], "a": 1, "e": "চোখ থেকে জল বিচ্যুত হচ্ছে।"},
  {"q": "‘ছাদে বৃষ্টি পড়ে’ - ‘ছাদে’ কোন কারক?", "o": ["অধিকরণ", "অপাদান", "করণ", "কর্ম"], "a": 0, "e": "ছাদ এখানে আধার।"},
  {"q": "‘ছাদ থেকে জল পড়ে’ - ‘ছাদ থেকে’ কোন কারক?", "o": ["অপাদান", "অধিকরণ", "করণ", "কর্ম"], "a": 0, "e": "বিচ্যুত হওয়া বোঝাচ্ছে।"},
  {"q": "‘বিদ্বানকে আদর করো’ - ‘বিদ্বানকে’ কোন কারক?", "o": ["কর্ম", "কর্তা", "করণ", "সম্প্রদান"], "a": 0, "e": "কাকে আদর করো? বিদ্বানকে।"},
  {"q": "‘নদীর জল মিষ্টি’ - ‘নদীর’ কোন পদ?", "o": ["সম্বন্ধ পদ", "কর্তা", "কর্ম", "অধিকরণ"], "a": 0, "e": "র/এর বিভক্তিযুক্ত পদ সম্বন্ধ পদ।"},
  {"q": "‘বসন্তে কোকিল ডাকে’ - ‘বসন্তে’ কোন কারক?", "o": ["অধিকরণ", "অপাদান", "করণ", "কর্ম"], "a": 0, "e": "কাল বা সময় বোঝাচ্ছে।"},
  {"q": "‘ব্যায়ামে শরীর ভালো থাকে’ - ‘ব্যায়ামে’ কোন কারক?", "o": ["করণ", "কর্তা", "কর্ম", "অধিকরণ"], "a": 0, "e": "ব্যায়ামের দ্বারা শরীর ভালো থাকে।"},
  {"q": "‘কলমে লেখা হয়’ - ‘কলমে’ কোন কারক?", "o": ["করণ", "কর্তা", "কর্ম", "অধিকরণ"], "a": 0, "e": "কলম লেখার উপকরণ বা যন্ত্র।"},
  {"q": "‘মন দিয়া করো সব কাজ’ - ‘মন দিয়া’ কোন কারক?", "o": ["করণ", "কর্তা", "কর্ম", "অধিকরণ"], "a": 0, "e": "মন এখানে মাধ্যম।"},
  {"q": "‘দুধ থেকে দই হয়’ - ‘দুধ থেকে’ কোন কারক?", "o": ["অপাদান", "অধিকরণ", "করণ", "কর্ম"], "a": 0, "e": "উৎপন্ন হওয়া বোঝালে অপাদান।"},
  {"q": "‘বনে বাঘ আছে’ - ‘বনে’ কোন কারক?", "o": ["অধিকরণ", "অপাদান", "করণ", "কর্ম"], "a": 0, "e": "বন এখানে স্থান।"},
  {"q": "‘মেঘে বৃষ্টি হয়’ - ‘মেঘে’ কোন কারক?", "o": ["অপাদান", "অধিকরণ", "করণ", "কর্ম"], "a": 0, "e": "মেঘ থেকে বিচ্যুত বা উৎপন্ন।"},
  {"q": "‘সূর্যোদয়ে অন্ধকার দূরীভূত হয়’ - ‘সূর্যোদয়ে’ কোন কারক?", "o": ["ভাবাধিকরণ", "আধারাধিকরণ", "কালাধিকরণ", "অপাদান"], "a": 0, "e": "একটি ক্রিয়ার দ্বারা অন্যটি ঘটলে ভাবাধিকরণ।"},
  {"q": "‘অধিকরণ কারক কয় প্রকার?’", "o": ["২ প্রকার", "৩ প্রকার", "৪ প্রকার", "৫ প্রকার"], "a": 1, "e": "কালাধিকরণ, আধারাধিকরণ ও ভাবাধিকরণ।"},
  {"q": "‘জিজ্ঞাসিব জনে জনে’ - ‘জনে জনে’ কোন কারক?", "o": ["কর্ম", "কর্তা", "করণ", "অধিকরণ"], "a": 0, "e": "কাকে জিজ্ঞাসা করব? উত্তর কর্মকারক।"},
  {"q": "‘আমাকে যেতে হবে’ - ‘আমাকে’ কোন কারক?", "o": ["কর্তা", "কর্ম", "করণ", "অধিকরণ"], "a": 0, "e": "যাওয়ার কাজটি আমার দ্বারা হবে।"},
  {"q": "‘রাজায় রাজায় লড়াই’ - এটি কোন কর্তা?", "o": ["ব্যতিহার কর্তা", "প্রযোজ্য কর্তা", "প্রযোজক কর্তা", "মুখ্য কর্তা"], "a": 0, "e": "উভয়ে একই কাজ করলে ব্যতিহার কর্তা হয়।"},
  {"q": "‘ঘোড়ায় গাড়ি টানে’ - ‘ঘোড়ায়’ কোন কারক?", "o": ["কর্তা", "কর্ম", "করণ", "অপাদান"], "a": 0, "e": "ঘোড়া এখানে কার্য সম্পাদনকারী।"},
  {"q": "‘খিলে পানটা খাবে’ - ‘খিলে’ কোন কারক?", "o": ["অধিকরণ", "কর্ম", "করণ", "অপাদান"], "a": 0, "e": "খিলি বা পানের ভেতরের স্থান।"},
  {"q": "‘মরণরে তুঁহুঁ মম শ্যাম সমান’ - ‘মরণরে’ কোন কারক?", "o": ["কর্ম", "কর্তা", "করণ", "অধিকরণ"], "a": 0, "e": "মরণকে উদ্দেশ্য করে বলা।"},
  {"q": "‘বাবাকে বড্ড ভয় পাই’ - ‘বাবাকে’ কোন কারক?", "o": ["অপাদান", "কর্ম", "কর্তা", "অধিকরণ"], "a": 0, "e": "ভয় পাওয়া বোঝালে অপাদান হয়।"},
  {"q": "‘তরণী হুকুমে চলে’ - ‘হুকুমে’ কোন কারক?", "o": ["করণ", "কর্তা", "কর্ম", "অধিকরণ"], "a": 0, "e": "হুকুমের মাধ্যমে বা উপায়ে।"},
  {"q": "‘আকাশে তো আমি রাখি নাই মোর ওড়ার চিহ্ন’ - ‘আকাশে’ কোন কারক?", "o": ["অধিকরণ", "অপাদান", "করণ", "কর্ম"], "a": 0, "e": "আকাশ স্থানবাচক অধিকরণ।"},
  {"q": "‘সমিতিতে চাঁদা দাও’ - ‘সমিতিতে’ কোন কারক?", "o": ["সম্প্রদান", "কর্ম", "করণ", "অধিকরণ"], "a": 0, "e": "সমিতিতে চাঁদা দেওয়া সম্প্রদান বা নিমিত্ত।"},
  {"q": "‘তিনি ব্যাকরণে পণ্ডিত’ - ‘ব্যাকরণে’ কোন কারক?", "o": ["অধিকরণ", "অপাদান", "করণ", "কর্ম"], "a": 0, "e": "বিষয় বোঝালে বৈষয়িক অধিকরণ হয়।"},
  {"q": "‘অন্ধজনে দেহ আলো’ - ‘অন্ধজনে’ কোন কারক?", "o": ["সম্প্রদান", "কর্ম", "করণ", "অধিকরণ"], "a": 0, "e": "নিঃস্বার্থ উপকার বা দান সম্প্রদান।"},
  {"q": "‘বাঘে মহিষে এক ঘাটে জল খায়’ - এটি কোন কর্তা?", "o": ["ব্যতিহার কর্তা", "প্রযোজক কর্তা", "প্রযোজ্য কর্তা", "মুখ্য কর্তা"], "a": 0, "e": "দুটি কর্তা একই কাজ করলে ব্যতিহার।"},
  {"q": "‘শিকারি বিড়াল গোঁফে চেনা যায়’ - ‘গোঁফে’ কোন কারক?", "o": ["করণ", "অধিকরণ", "কর্তা", "কর্ম"], "a": 0, "e": "লক্ষ্মণ বা চিহ্ন বোঝালে করণ কারক হয়।"},
  {"q": "‘গাড়ি স্টেশন ছাড়ল’ - ‘স্টেশন’ কোন কারক?", "o": ["অপাদান", "অধিকরণ", "করণ", "কর্ম"], "a": 0, "e": "বিচ্যুত হওয়া বোঝাচ্ছে।"},
  {"q": "‘জেলেরা মাছ ধরছে’ - ‘জেলেরা’ কোন কারক?", "o": ["কর্তা", "কর্ম", "করণ", "অধিকরণ"], "a": 0, "e": "জেলেরা এখানে ক্রিয়ার কর্তা।"},
  {"q": "‘গাছে ফল ধরেছে’ - ‘গাছে’ কোন কারক?", "o": ["অধিকরণ", "অপাদান", "করণ", "কর্ম"], "a": 0, "e": "গাছ এখানে আধার।"},
  {"q": "‘তিল থেকে তেল হয়’ - ‘তিল থেকে’ কোন কারক?", "o": ["অপাদান", "অধিকরণ", "করণ", "কর্ম"], "a": 0, "e": "উৎপন্ন হওয়া বোঝাচ্ছে।"},
  {"q": "‘পাপে বিরত হও’ - ‘পাপে’ কোন কারক?", "o": ["অপাদান", "অধিকরণ", "করণ", "কর্ম"], "a": 0, "e": "বিরত হওয়া বোঝালে অপাদান হয়।"},
  {"q": "‘বাড়ি যাও’ - ‘বাড়ি’ কোন কারক?", "o": ["অধিকরণ", "কর্ম", "করণ", "অপাদান"], "a": 0, "e": "স্থান বোঝাচ্ছে।"},
  {"q": "‘অহঙ্কার পতনের মূল’ - ‘অহঙ্কার’ কোন কারক?", "o": ["করণ", "কর্তা", "কর্ম", "অপাদান"], "a": 0, "e": "অহঙ্কারের দ্বারা পতন ঘটে।"},
  {"q": "‘সূর্য উঠলে আধার কাটে’ - ‘সূর্য’ কোন কারক?", "o": ["কর্তা (নিরপেক্ষ)", "কর্ম", "করণ", "অধিকরণ"], "a": 0, "e": "অসমাপিকা ক্রিয়ার কর্তা নিরপেক্ষ কর্তা।"},
  {"q": "‘লোকটা কানে কালা’ - ‘কানে’ কোন কারক?", "o": ["করণ", "অধিকরণ", "কর্তা", "কর্ম"], "a": 0, "e": "অঙ্গহানি বা চিহ্ন বোঝালে করণ।"},
  {"q": "‘পরার্থে জীবন দাও’ - ‘পরার্থে’ কোন কারক?", "o": ["সম্প্রদান", "কর্ম", "করণ", "অধিকরণ"], "a": 0, "e": "নিমিত্ত বা অন্যের তরে দান।"},
  {"q": "‘খাবার দাও’ - ‘খাবার’ কোন কারক?", "o": ["কর্ম", "কর্তা", "করণ", "অধিকরণ"], "a": 0, "e": "কী দাও? উত্তর খাবার।"},
  {"q": "‘সকালে বাতাস বয়’ - ‘সকালে’ কোন কারক?", "o": ["অধিকরণ", "অপাদান", "করণ", "কর্ম"], "a": 0, "e": "সময়বাচক অধিকরণ।"},
  {"q": "‘আমায় একখানা বই দাও’ - ‘আমায়’ কোন কারক?", "o": ["কর্ম", "সম্প্রদান", "কর্তা", "অধিকরণ"], "a": 0, "e": "কাকে দাও? আমায়।"},
  {"q": "‘শিক্ষককে শ্রদ্ধা করো’ - ‘শিক্ষককে’ কোন কারক?", "o": ["কর্ম", "সম্প্রদান", "কর্তা", "অধিকরণ"], "a": 0, "e": "শ্রদ্ধা করার পাত্র কর্মকারক।"},
  {"q": "‘হাতে কলমে শেখো’ - ‘হাতে কলমে’ কোন কারক?", "o": ["করণ", "অধিকরণ", "কর্তা", "কর্ম"], "a": 0, "e": "কাজের উপায়।"},
  {"q": "‘শীতে কাঁপছি’ - ‘শীতে’ কোন কারক?", "o": ["করণ", "অধিকরণ", "কর্তা", "অপাদান"], "a": 0, "e": "শীতের কারণে বা দ্বারা কাঁপছি।"},
  {"q": "‘রেলে ভ্রমণ আরামদায়ক’ - ‘রেলে’ কোন কারক?", "o": ["করণ", "অধিকরণ", "কর্তা", "কর্ম"], "a": 0, "e": "ভ্রমণের মাধ্যম বা যন্ত্র।"},
  {"q": "‘নদী পথে যাব’ - ‘নদী পথে’ কোন কারক?", "o": ["অধিকরণ", "করণ", "কর্তা", "কর্ম"], "a": 0, "e": "পথ বা স্থান বোঝাচ্ছে।"},
  {"q": "‘মা শিশুকে চাঁদ দেখাচ্ছেন’ - ‘শিশুকে’ কোন কারক?", "o": ["প্রযোজ্য কর্তা", "প্রযোজক কর্তা", "মুখ্য কর্তা", "কর্ম"], "a": 0, "e": "যাকে দিয়ে কাজটি করানো হচ্ছে।"},
  {"q": "‘ভিক্ষা দাও দেখি’ - ‘নিমিত্ত’ অর্থে কোনটি?", "o": ["সম্প্রদান", "কর্ম", "করণ", "অধিকরণ"], "a": 0, "e": "নিঃস্বার্থভাবে কিছু প্রদান।"},
  {"q": "‘টাকায় কিনা হয়’ - ‘টাকায়’ কোন কারক?", "o": ["করণ", "কর্তা", "কর্ম", "অধিকরণ"], "a": 0, "e": "টাকার দ্বারা।"},
  {"q": "‘বিপদ থেকে বাঁচাও’ - ‘বিপদ থেকে’ কোন কারক?", "o": ["অপাদান", "অধিকরণ", "করণ", "কর্ম"], "a": 0, "e": "বিপদ হতে মুক্তি বা রক্ষা।"},
  {"q": "‘বনে পশু থাকে’ - ‘বনে’ কোন কারক?", "o": ["অধিকরণ", "অপাদান", "করণ", "কর্ম"], "a": 0, "e": "স্থানবাচক।"},
  {"q": "‘লৌহ দ্বারা নির্মিত’ - ‘লৌহ দ্বারা’ কোন কারক?", "o": ["করণ", "কর্তা", "কর্ম", "অধিকরণ"], "a": 0, "e": "উপকরণ বা মাধ্যম।"},
  {"q": "‘সে ভাত খায়’ - ‘ভাত’ কোন কারক?", "o": ["কর্ম", "কর্তা", "করণ", "অপাদান"], "a": 0, "e": "কী খায়? ভাত।"},
  {"q": "‘রাজাকে সেলাম করো’ - ‘রাজাকে’ কোন কারক?", "o": ["কর্ম", "সম্প্রদান", "কর্তা", "অধিকরণ"], "a": 0, "e": "সম্মান জানানো কর্মকারক।"},
  {"q": "‘সে অঙ্কে কাঁচা’ - ‘অঙ্কে’ কোন কারক?", "o": ["অধিকরণ (বৈষয়িক)", "অপাদান", "করণ", "কর্ম"], "a": 0, "e": "নির্দিষ্ট বিষয়ে দক্ষতা বা অক্ষমতা।"},
  {"q": "‘রাতে তারা দেখা যায়’ - ‘রাতে’ কোন কারক?", "o": ["অধিকরণ", "অপাদান", "করণ", "কর্ম"], "a": 0, "e": "সময়বাচক।"},
  {"q": "‘পরাজয়ে ডরে না বীর’ - ‘পরাজয়ে’ কোন কারক?", "o": ["অপাদান", "অধিকরণ", "করণ", "কর্ম"], "a": 0, "e": "ভয় পাওয়া অর্থে অপাদান।"},
  {"q": "‘জলে কুমির থাকে’ - ‘জলে’ কোন কারক?", "o": ["অধিকরণ", "অপাদান", "করণ", "কর্ম"], "a": 0, "e": "আধার বা স্থান।"},
  {"q": "‘মেঘ হতে বৃষ্টি পড়ে’ - ‘মেঘ হতে’ কোন কারক?", "o": ["অপাদান", "অধিকরণ", "করণ", "কর্ম"], "a": 0, "e": "বিচ্যুত হওয়া।"},
  {"q": "‘হাতে আংটিটি মানিয়েছে’ - ‘হাতে’ কোন কারক?", "o": ["অধিকরণ", "অপাদান", "করণ", "কর্ম"], "a": 0, "e": "স্থানবাচক অধিকরণ।"},
  {"q": "‘তিনি ঢাকা গেছেন’ - ‘ঢাকা’ কোন কারক?", "o": ["অধিকরণ", "কর্ম", "করণ", "অপাদান"], "a": 0, "e": "গন্তব্য বা স্থান।"},
  {"q": "‘দুঃখের দিন শেষ হবে’ - ‘দুঃখের’ কোন পদ?", "o": ["সম্বন্ধ পদ", "কর্তা", "কর্ম", "করণ"], "a": 0, "e": "অকর্মক পদের সাথে র/এর।"},
  {"q": "‘ফুল দিয়ে মালা গাঁথো’ - ‘ফুল দিয়ে’ কোন কারক?", "o": ["করণ", "কর্তা", "কর্ম", "অধিকরণ"], "a": 0, "e": "উপকরণ।"},
  {"q": "‘বিছানায় ঘুমাও’ - ‘বিছানায়’ কোন কারক?", "o": ["অধিকরণ", "অপাদান", "করণ", "কর্ম"], "a": 0, "e": "শয্যা বা স্থান।"},
  {"q": "‘মা রান্না করছেন’ - ‘মা’ কোন কারক?", "o": ["কর্তা", "কর্ম", "করণ", "অধিকরণ"], "a": 0, "e": "রান্নার কাজটি মা করছেন।"},
  {"q": "‘নদীর জল বয়ে চলে’ - ‘নদীর’ কোন পদ?", "o": ["সম্বন্ধ পদ", "অধিকরণ", "কর্তা", "কর্ম"], "a": 0, "e": "র/এর বিভক্তি।"},
  {"q": "‘বিপদ আপদ মানুষের আসে’ - ‘মানুষের’ কোন পদ?", "o": ["সম্বন্ধ পদ", "কর্তা", "কর্ম", "অধিকরণ"], "a": 0, "e": "সম্বন্ধবাচক।"},
  {"q": "‘সে কানে শোনে না’ - ‘কানে’ কোন কারক?", "o": ["করণ", "অধিকরণ", "কর্তা", "কর্ম"], "a": 0, "e": "ইন্দ্রিয় বা যন্ত্র।"},
  {"q": "‘বাঘকে ভয় পায় না কে?’ - ‘বাঘকে’ কোন কারক?", "o": ["অপাদান", "কর্ম", "কর্তা", "করণ"], "a": 0, "e": "ভীতির উৎস অপাদান।"},
  {"q": "‘একটু দুধ দাও’ - ‘দুধ’ কোন কারক?", "o": ["কর্ম", "কর্তা", "করণ", "অপাদান"], "a": 0, "e": "কী দাও? দুধ।"},
  {"q": "‘আমরা বল খেলি’ - ‘বল’ কোন কারক?", "o": ["করণ", "কর্ম", "কর্তা", "অধিকরণ"], "a": 1, "e": "এখানে 'বল' হলো খেলা বা কর্ম। যদি বলের দ্বারা বলা হতো তবে করণ হতো।"},
  {"q": "‘ছুরি দিয়ে আম কাটো’ - ‘ছুরি দিয়ে’ কোন কারক?", "o": ["করণ", "কর্তা", "কর্ম", "অধিকরণ"], "a": 0, "e": "ছুরি এখানে যন্ত্র।"},
  {"q": "‘দুধে মাখন হয়’ - ‘দুধে’ কোন কারক?", "o": ["অপাদান", "অধিকরণ", "করণ", "কর্ম"], "a": 0, "e": "উৎপন্ন হচ্ছে।"},
  {"q": "‘খাঁচায় পাখি নেই’ - ‘খাঁচায়’ কোন কারক?", "o": ["অধিকরণ", "অপাদান", "করণ", "কর্ম"], "a": 0, "e": "স্থানবাচক।"},
  {"q": "‘সে সকালে এসেছে’ - ‘সকালে’ কোন কারক?", "o": ["অধিকরণ", "অপাদান", "করণ", "কর্ম"], "a": 0, "e": "সময়বাচক।"},
  {"q": "‘রফিক বই পড়ছে’ - ‘রফিক’ কোন কারক?", "o": ["কর্তা", "কর্ম", "করণ", "অধিকরণ"], "a": 0, "e": "পড়ার কাজটি রফিক করছে।"},
  {"q": "‘বইটি টেবিলে আছে’ - ‘টেবিলে’ কোন কারক?", "o": ["অধিকরণ", "অপাদান", "করণ", "কর্ম"], "a": 0, "e": "স্থানবাচক।"},
  {"q": "‘বৃষ্টিতে ভেজা নিষেধ’ - ‘বৃষ্টিতে’ কোন কারক?", "o": ["করণ", "অধিকরণ", "কর্তা", "অপাদান"], "a": 0, "e": "বৃষ্টির দ্বারা ভেজা।"},
  {"q": "‘কলমটি ভালো লেখে’ - ‘কলমটি’ কোন কারক?", "o": ["কর্তা", "করণ", "কর্ম", "অধিকরণ"], "a": 0, "e": "কলম এখানে কাজ করছে (কর্তৃরূপে)।"},
  {"q": "‘বাবা বাড়ি নেই’ - ‘বাড়ি’ কোন কারক?", "o": ["অধিকরণ", "কর্ম", "করণ", "অপাদান"], "a": 0, "e": "স্থান।"},
  {"q": "‘বাঘের ডাক শোনা যায়’ - ‘বাঘের’ কোন পদ?", "o": ["সম্বন্ধ পদ", "কর্তা", "কর্ম", "অধিকরণ"], "a": 0, "e": "র/এর বিভক্তি।"},
  {"q": "‘নদীতে মাছ আছে’ - ‘নদীতে’ কোন কারক?", "o": ["অধিকরণ", "অপাদান", "করণ", "কর্ম"], "a": 0, "e": "স্থানবাচক।"},
  {"q": "‘ডাল থেকে ফল পড়ল’ - ‘ডাল থেকে’ কোন কারক?", "o": ["অপাদান", "অধিকরণ", "করণ", "কর্ম"], "a": 0, "e": "বিচ্যুত হওয়া।"},
  {"q": "‘অন্ধকারে ভয় লাগে’ - ‘অন্ধকারে’ কোন কারক?", "o": ["অপাদান", "অধিকরণ", "করণ", "কর্ম"], "a": 0, "e": "ভীতির উৎস।"},
  {"q": "‘তিনি সাঁতারে পটু’ - ‘সাঁতারে’ কোন কারক?", "o": ["অধিকরণ", "অপাদান", "করণ", "কর্ম"], "a": 0, "e": "বৈষয়িক অধিকরণ।"},
  {"q": "‘সে রিকশায় এল’ - ‘রিকশায়’ কোন কারক?", "o": ["করণ", "অধিকরণ", "কর্তা", "কর্ম"], "a": 0, "e": "মাধ্যম বা যন্ত্র।"},
  {"q": "‘মন দিয়ে পড়াশোনা করো’ - ‘মন দিয়ে’ কোন কারক?", "o": ["করণ", "কর্তা", "কর্ম", "অধিকরণ"], "a": 0, "e": "উপকরণ বা মাধ্যম।"},
  {"q": "‘সে দুপুরে খাবে’ - ‘দুপুরে’ কোন কারক?", "o": ["অধিকরণ", "অপাদান", "করণ", "কর্ম"], "a": 0, "e": "সময়বাচক।"},
  {"q": "‘গরুতে দুধ দেয়’ - ‘গরুতে’ কোন কারক?", "o": ["কর্তা", "কর্ম", "করণ", "অধিকরণ"], "a": 0, "e": "দুধ দেওয়ার কাজটি গরু করে।"},
  {"q": "‘মাছ পানিতে বাস করে’ - ‘পানিতে’ কোন কারক?", "o": ["অধিকরণ", "অপাদান", "করণ", "কর্ম"], "a": 0, "e": "আধার বা স্থান।"},
  {"q": "‘শিক্ষককে মান্য করো’ - ‘শিক্ষককে’ কোন কারক?", "o": ["কর্ম", "সম্প্রদান", "কর্তা", "অধিকরণ"], "a": 0, "e": "যাকে মান্য করা হয়।"},
  {"q": "‘সূর্য থেকে আলো পাই’ - ‘সূর্য থেকে’ কোন কারক?", "o": ["অপাদান", "অধিকরণ", "করণ", "কর্ম"], "a": 0, "e": "গৃহীত বা উৎপন্ন হওয়া।"},
  {"q": "‘বিপদে ধৈর্য ধরো’ - ‘বিপদে’ কোন কারক?", "o": ["অধিকরণ", "অপাদান", "করণ", "কর্ম"], "a": 0, "e": "অবস্থা বা সময়।"},
  {"q": "‘চোখে ছানি পড়েছে’ - ‘চোখে’ কোন কারক?", "o": ["অধিকরণ", "অপাদান", "করণ", "কর্ম"], "a": 0, "e": "স্থানবাচক।"},
  {"q": "‘বইটি আমার’ - ‘আমার’ কোন পদ?", "o": ["সম্বন্ধ পদ", "কর্তা", "কর্ম", "অধিকরণ"], "a": 0, "e": "মালিকানা বা র/এর।"},
  {"q": "‘মাঠে ফসল ফলেছে’ - ‘মাঠে’ কোন কারক?", "o": ["অধিকরণ", "অপাদান", "করণ", "কর্ম"], "a": 0, "e": "স্থানবাচক।"},
  {"q": "‘টাকা দিয়ে বই কেনো’ - ‘টাকা দিয়ে’ কোন কারক?", "o": ["করণ", "কর্তা", "কর্ম", "অধিকরণ"], "a": 0, "e": "মাধ্যম।"},
  {"q": "‘সে হেঁটে স্কুলে যায়’ - ‘হেঁটে’ কোন কারক?", "o": ["করণ", "কর্তা", "কর্ম", "অধিকরণ"], "a": 0, "e": "উপায়।"},
  {"q": "‘চাঁদনী রাতে সব সুন্দর’ - ‘চাঁদনী রাতে’ কোন কারক?", "o": ["অধিকরণ", "অপাদান", "করণ", "কর্ম"], "a": 0, "e": "সময়বাচক।"},
  {"q": "‘গরিবকে অর্থ দাও’ - ‘গরিবকে’ কোন কারক?", "o": ["সম্প্রদান", "কর্ম", "করণ", "অধিকরণ"], "a": 0, "e": "নিঃস্বার্থ দান।"},
  {"q": "‘বিপদ থেকে মুক্তি’ - ‘বিপদ থেকে’ কোন কারক?", "o": ["অপাদান", "অধিকরণ", "করণ", "কর্ম"], "a": 0, "e": "মুক্তি বা বিচ্যুতি।"},
  {"q": "‘ছাদ থেকে বাগান দেখা যায়’ - ‘ছাদ থেকে’ কোন কারক?", "o": ["অধিকরণ", "অপাদান", "করণ", "কর্ম"], "a": 0, "e": "যে স্থান থেকে দেখা যায়।"},
  {"q": "‘সে বল খেলে’ - ‘বল’ কোন কারক?", "o": ["কর্ম", "করণ", "কর্তা", "অধিকরণ"], "a": 0, "e": "খেলার বিষয়।"},
  {"q": "‘চাবুক দিয়ে মারা’ - ‘চাবুক দিয়ে’ কোন কারক?", "o": ["করণ", "কর্তা", "কর্ম", "অধিকরণ"], "a": 0, "e": "যন্ত্র বা উপকরণ।"},
  {"q": "‘বইটি কার?’ - ‘কার’ কোন পদ?", "o": ["সম্বন্ধ পদ", "কর্তা", "কর্ম", "অধিকরণ"], "a": 0, "e": "প্রশ্নবাচক সম্বন্ধ পদ।"},
  {"q": "‘গাছ থেকে পাতা পড়ে’ - ‘গাছ থেকে’ কোন কারক?", "o": ["অপাদান", "অধিকরণ", "করণ", "কর্ম"], "a": 0, "e": "বিচ্যুত হওয়া।"},
  {"q": "‘সে ঢাকায় থাকে’ - ‘ঢাকায়’ কোন কারক?", "o": ["অধিকরণ", "অপাদান", "করণ", "কর্ম"], "a": 0, "e": "স্থানবাচক।"},
  {"q": "‘মা আমাকে গল্প শোনান’ - ‘আমাকে’ কোন কারক?", "o": ["প্রযোজ্য কর্তা", "প্রযোজক কর্তা", "মুখ্য কর্তা", "কর্ম"], "a": 0, "e": "গল্প শোনার কাজটি আমি করছি।"},
  {"q": "‘বাবা আমায় ডাকেন’ - ‘আমায়’ কোন কারক?", "o": ["কর্ম", "কর্তা", "করণ", "অধিকরণ"], "a": 0, "e": "কাকে ডাকেন? আমায়।"},
  {"q": "‘মেঘ দেখে ভয় পেয়ো না’ - ‘মেঘ দেখে’ কোন কারক?", "o": ["অপাদান", "অধিকরণ", "করণ", "কর্ম"], "a": 0, "e": "ভীতির কারণ।"},
  {"q": "‘তিনি গানে পারদর্শী’ - ‘গানে’ কোন কারক?", "o": ["অধিকরণ", "অপাদান", "করণ", "কর্ম"], "a": 0, "e": "বৈষয়িক অধিকরণ।"},
  {"q": "‘নদীতে জোয়ার আসে’ - ‘নদীতে’ কোন কারক?", "o": ["অধিকরণ", "অপাদান", "করণ", "কর্ম"], "a": 0, "e": "স্থানবাচক।"},
  {"q": "‘হাতে সময় নেই’ - ‘হাতে’ কোন কারক?", "o": ["অধিকরণ", "অপাদান", "করণ", "কর্ম"], "a": 0, "e": "সময় বা অবস্থা।"},
  {"q": "‘আকাশে মেঘ জমেছে’ - ‘আকাশে’ কোন কারক?", "o": ["অধিকরণ", "অপাদান", "করণ", "কর্ম"], "a": 0, "e": "স্থানবাচক।"},
  {"q": "‘মাঠে গরু চরছে’ - ‘মাঠে’ কোন কারক?", "o": ["অধিকরণ", "অপাদান", "করণ", "কর্ম"], "a": 0, "e": "স্থানবাচক।"},
  {"q": "‘মশা মারতে কামান দাগা’ - ‘কামান’ কোন কারক?", "o": ["করণ", "কর্তা", "কর্ম", "অধিকরণ"], "a": 0, "e": "উপকরণ বা যন্ত্র।"},
  {"q": "‘ফুল তোলা নিষেধ’ - ‘ফুল’ কোন কারক?", "o": ["কর্ম", "কর্তা", "করণ", "অধিকরণ"], "a": 0, "e": "কী তোলা নিষেধ? ফুল।"}
]
